unagi/__init__.py
unagi/camera.py
unagi/catalog.py
unagi/config.py
unagi/filters.py
unagi/hsc.py
unagi/mask.py
unagi/plotting.py
unagi/query.py
unagi/sky.py
unagi/target.py
unagi/task.py
unagi/utils.py
unagi/data/.gitignore
unagi/data/camera/primary_mirror.lis
unagi/data/camera/qe_ccd_HSC.txt
unagi/data/camera/subaru_m1_r_20171010.txt
unagi/data/camera/subaru_m1_r_20171023.txt
unagi/data/camera/subaru_m1_r_20180129.txt
unagi/data/camera/subaru_m1_r_20180307.txt
unagi/data/camera/subaru_m1_r_20180418.txt
unagi/data/camera/subaru_m1_r_20180419.txt
unagi/data/camera/subaru_m1_r_20180521.txt
unagi/data/camera/subaru_m1_r_20180621.txt
unagi/data/camera/subaru_m1_r_20180723.txt
unagi/data/camera/subaru_m1_r_20180815.txt
unagi/data/camera/subaru_m1_r_20181012.txt
unagi/data/camera/subaru_m1_r_20181107.txt
unagi/data/camera/subaru_m1_r_20181221.txt
unagi/data/camera/subaru_m1_r_20190131.txt
unagi/data/camera/subaru_m1_r_20190201.txt
unagi/data/camera/subaru_m1_r_20190208.txt
unagi/data/camera/subaru_m1_r_20190311.txt
unagi/data/camera/subaru_m1_r_20190426-2.txt
unagi/data/camera/subaru_m1_r_20190426.txt
unagi/data/camera/throughput_popt2.txt
unagi/data/camera/throughput_win.txt
unagi/data/camera/vignetting.txt
unagi/data/filters/hsc_filters_origin_center.xml
unagi/data/filters/hsc_filters_origin_weighted.xml
unagi/data/filters/hsc_filters_total.xml
unagi/data/filters/origin/HSC-G.json
unagi/data/filters/origin/HSC-G.par
unagi/data/filters/origin/HSC-I.json
unagi/data/filters/origin/HSC-I.par
unagi/data/filters/origin/HSC-I2.json
unagi/data/filters/origin/HSC-I2.par
unagi/data/filters/origin/HSC-NB387.json
unagi/data/filters/origin/HSC-NB387.par
unagi/data/filters/origin/HSC-NB387.txt
unagi/data/filters/origin/HSC-NB816.json
unagi/data/filters/origin/HSC-NB816.par
unagi/data/filters/origin/HSC-NB816.txt
unagi/data/filters/origin/HSC-NB921.json
unagi/data/filters/origin/HSC-NB921.par
unagi/data/filters/origin/HSC-NB921.txt
unagi/data/filters/origin/HSC-R.json
unagi-0.1.3.dev13.dist-info/LICENSE
unagi-0.1.3.dev13.dist-info/METADATA
unagi-0.1.3.dev13.dist-info/WHEEL
unagi-0.1.3.dev13.dist-info/top_level.txt
unagi-0.1.3.dev13.dist-info/RECORD
