Metadata-Version: 2.1
Name: unagi
Version: 0.1.3.dev13
Summary: Delicious Data from Hyper Suprime-Cam Survey!
Home-page: https://github.com/dr-guangtou/unagi
Author: Song Huang
Author-email: shuang89@ucsc.edu
License: MIT
Keywords: astronomy
Platform: UNKNOWN
Classifier: Development Status :: 4 - Beta
Classifier: License :: OSI Approved :: MIT License
Classifier: Intended Audience :: Science/Research
Classifier: Topic :: Scientific/Engineering :: Astronomy
Classifier: Operating System :: OS Independent
Classifier: Programming Language :: Python :: 3 :: Only
Classifier: Programming Language :: Python :: 3
Classifier: Programming Language :: Python :: 3.6
Classifier: Programming Language :: Python :: 3.7
Requires-Python: >=3.6
Requires-Dist: six
Requires-Dist: numpy
Requires-Dist: scipy
Requires-Dist: pyparsing
Requires-Dist: astropy (>=3.0)
Requires-Dist: matplotlib (>=2.0)
Requires-Dist: fits2hdf (>=1.1.1)
Requires-Dist: tenacity (>=5.1.1)
Requires-Dist: requests
